begoneads/__init__.py
begoneads/begoneads.py
begoneads/exceptions.py
begoneads/helpers.py
begoneads/hostsmanager.py
begoneads/hostsmanager_test.py
begoneads/collectors/__init__.py
begoneads/collectors/base_collector.py
begoneads/collectors/local_collector.py
begoneads/collectors/remote_collector.py
begoneads/collectors/remote_collector_test.py
begoneads-0.0.10.dist-info/LICENSE.md
begoneads-0.0.10.dist-info/METADATA
begoneads-0.0.10.dist-info/WHEEL
begoneads-0.0.10.dist-info/entry_points.txt
begoneads-0.0.10.dist-info/top_level.txt
begoneads-0.0.10.dist-info/RECORD
