Metadata-Version: 2.1
Name: begoneads
Version: 0.0.10
Summary: BeGoneAds puts some popular hosts file lists into the hosts file as a adblocker measure.
Home-page: http://github.com/anned20/begoneads
Author: Anne Douwe Bouma
Author-email: annedouwe@bouma.tech
License: MIT
Classifier: Development Status :: 3 - Alpha
Classifier: License :: OSI Approved :: MIT License
Classifier: Programming Language :: Python :: 3.6
Classifier: Programming Language :: Python :: 3.7
Classifier: Programming Language :: Python :: 3.8
Classifier: Topic :: System :: Networking
Requires-Python: >=3.6
License-File: LICENSE.md
Requires-Dist: click
Requires-Dist: requests
Requires-Dist: tqdm
